MANIFEST.in
README.rst
setup.py
abcEconomics/__init__.py
abcEconomics/agent.py
abcEconomics/compile.py
abcEconomics/expiringgood.py
abcEconomics/goods.py
abcEconomics/group.py
abcEconomics/inventory.py
abcEconomics/messenger.py
abcEconomics/multiprocess.py
abcEconomics/notenoughgoods.py
abcEconomics/show.py
abcEconomics/singleprocess.py
abcEconomics/trade.py
abcEconomics/trade.pyx
abcEconomics.egg-info/PKG-INFO
abcEconomics.egg-info/SOURCES.txt
abcEconomics.egg-info/dependency_links.txt
abcEconomics.egg-info/requires.txt
abcEconomics.egg-info/top_level.txt
abcEconomics/agents/__init__.py
abcEconomics/agents/firm.py
abcEconomics/agents/household.py
abcEconomics/contracts/__init__.py
abcEconomics/contracts/contracting.py
abcEconomics/contracts/contracts.py
abcEconomics/contracts/flexiblecontracting.py
abcEconomics/gui/__init__.py
abcEconomics/gui/basiclayout.py
abcEconomics/gui/bokehwidget.py
abcEconomics/gui/dockpanel.py
abcEconomics/gui/form.py
abcEconomics/gui/loadform.py
abcEconomics/gui/make_graphs.py
abcEconomics/gui/webtext.py
abcEconomics/logger/__init__.py
abcEconomics/logger/db.py
abcEconomics/logger/logger.py
abcEconomics/logger/online_variance.c
abcEconomics/logger/online_variance.pxd
abcEconomics/logger/online_variance.py
abcEconomics/logger/online_variance.pyx
abcEconomics/logger/postprocess.py
unittest/aggregate_agent.csv
unittest/aggregate_friendly_agent.csv
unittest/aggregated_agent.csv
unittest/aggregated_friendly_agent.csv
unittest/ball.py
unittest/ball.pyc
unittest/buy.py
unittest/buy.pyc
unittest/buyexpiringcapital.py
unittest/buyexpiringcapital.pyc
unittest/expiringcapital.py
unittest/expiringcapital.pyc
unittest/give.py
unittest/give.pyc
unittest/giveexpiringcapital.py
unittest/giveexpiringcapital.pyc
unittest/killer.py
unittest/killer.pyc
unittest/logger_test.py
unittest/logger_test.pyc
unittest/messagea.py
unittest/messagea.pyc
unittest/messageb.py
unittest/messageb.pyc
unittest/panel_agent.csv
unittest/panel_friendly_agent.csv
unittest/parameter.db
unittest/production_firm.pyc
unittest/production_multifirm.py
unittest/production_multifirm.pyc
unittest/profile.prof
unittest/profile.sh
unittest/quote_buy.py
